raindrop_io_py-0.4.7.dist-info/licenses/LICENSE
raindropiopy/__init__.py
raindropiopy/api.py
raindropiopy/models.py
raindrop_io_py-0.4.7.dist-info/METADATA
raindrop_io_py-0.4.7.dist-info/WHEEL
raindrop_io_py-0.4.7.dist-info/top_level.txt
raindrop_io_py-0.4.7.dist-info/RECORD
