Metadata-Version: 2.4
Name: raindrop-io-py
Version: 0.4.7
Summary: API for Raindrop.io bookmark manager
Author: Peter Borocz <peter.borocz+raindrop-io-py@google.com>
Project-URL: Homepage, https://github.com/PBorocz/raindrop-io-py
Project-URL: Documentation, https://raindrop-io-py.rtfd.io
Keywords: python
Classifier: License :: OSI Approved :: MIT License
Classifier: Programming Language :: Python :: 3
Requires-Python: <4.0,>=3.10
License-File: LICENSE
Requires-Dist: python-dotenv>=1.0.0
Requires-Dist: requests-oauthlib>=1.3.1
Requires-Dist: pydantic<3.0,>=1.10.4
Requires-Dist: email-validator>=2.1.0
Requires-Dist: urllib3<2.7,>=2.6
Dynamic: license-file
